{ "type": "FeatureCollection", "crs": { "type": "name", "properties": { "name": "urn:ogc:def:crs:OGC:1.3:CRS84" } }, "features": [ 
{ "type": "Feature", "properties": { "Name": "hilagutfreund", "Description": "Mon Dec  2 21:18:13 EST 2013; Location Accuracy: " }, "geometry": { "type": "Point", "coordinates": [ , , 0.0 ] } },
{ "type": "Feature", "properties": { "Name": "William Falk-Wallace", "Description": "Mon Dec  2 20:14:49 EST 2013; Location Accuracy: 65.000000" }, "geometry": { "type": "Point", "coordinates": [ -73.959932, 40.808947, 0.0 ] } },
<<<<<<< HEAD
{ "type": "Feature", "properties": { "Name": "William Falk-Wallace", "Description": "Mon Dec  2 20:14:36 EST 2013; Location Accuracy: 65.000000" }, "geometry": { "type": "Point", "coordinates": [ -73.959944, 40.808954, 0.0 ] } },
=======
{ "type": "Feature", "properties": { "Name": "hilagutfreund", "Description": "Mon Dec  2 20:08:43 EST 2013; Location Accuracy: " }, "geometry": { "type": "Point", "coordinates": [ , , 0.0 ] } },
{ "type": "Feature", "properties": { "Name": "hilagutfreund", "Description": "Mon Dec  2 20:02:00 EST 2013; Location Accuracy: " }, "geometry": { "type": "Point", "coordinates": [ , , 0.0 ] } },
>>>>>>> 86064606f3cd988cbe54a97632faf169586c65de
{ "type": "Feature", "properties": { "Name": "William Falk-Wallace", "Description": "Mon Dec  2 19:56:51 EST 2013; Location Accuracy: 65.000000" }, "geometry": { "type": "Point", "coordinates": [ -73.959888, 40.808960, 0.0 ] } },
<<<<<<< HEAD
{ "type": "Feature", "properties": { "Name": "William Falk-Wallace", "Description": "Mon Dec  2 19:56:39 EST 2013; Location Accuracy: 65.000000" }, "geometry": { "type": "Point", "coordinates": [ -73.959888, 40.808960, 0.0 ] } },
{ "type": "Feature", "properties": { "Name": "William Falk-Wallace", "Description": "Mon Dec  2 19:56:14 EST 2013; Location Accuracy: 65.000000" }, "geometry": { "type": "Point", "coordinates": [ -73.959857, 40.808957, 0.0 ] } },
=======
{ "type": "Feature", "properties": { "Name": "hilagutfreund", "Description": "Mon Dec  2 19:51:00 EST 2013; Location Accuracy: " }, "geometry": { "type": "Point", "coordinates": [ , , 0.0 ] } },
{ "type": "Feature", "properties": { "Name": "hilagutfreund", "Description": "Mon Dec  2 19:33:15 EST 2013; Location Accuracy: " }, "geometry": { "type": "Point", "coordinates": [ , , 0.0 ] } },
<<<<<<< HEAD
{ "type": "Feature", "properties": { "Name": "hilagutfreund", "Description": "Mon Dec  2 19:28:20 EST 2013; Location Accuracy: " }, "geometry": { "type": "Point", "coordinates": [ , , 0.0 ] } },
<<<<<<< HEAD
{ "type": "Feature", "properties": { "Name": "hilagutfreund", "Description": "Mon Dec  2 19:25:12 EST 2013; Location Accuracy: " }, "geometry": { "type": "Point", "coordinates": [ , , 0.0 ] } },
{ "type": "Feature", "properties": { "Name": "hilagutfreund", "Description": "Mon Dec  2 19:24:14 EST 2013; Location Accuracy: " }, "geometry": { "type": "Point", "coordinates": [ , , 0.0 ] } },
=======
=======
>>>>>>> 869965e6a55898109ea0bd09699acad7eeab60b0
{ "type": "Feature", "properties": { "Name": "William Falk-Wallace", "Description": "Mon Dec  2 19:27:58 EST 2013; Location Accuracy: 65.000000" }, "geometry": { "type": "Point", "coordinates": [ -73.959598, 40.809020, 0.0 ] } },
{ "type": "Feature", "properties": { "Name": "William Falk-Wallace", "Description": "Mon Dec  2 19:27:32 EST 2013; Location Accuracy: 65.000000" }, "geometry": { "type": "Point", "coordinates": [ -73.959598, 40.809020, 0.0 ] } },
>>>>>>> 257a0ed2d77d7ffe862a883457e5829968d5b157
{ "type": "Feature", "properties": { "Name": "William Falk-Wallace", "Description": "Mon Dec  2 19:22:53 EST 2013; Location Accuracy: 65.000000" }, "geometry": { "type": "Point", "coordinates": [ -73.959568, 40.809041, 0.0 ] } },
>>>>>>> 7e52ac11f52653a03befcab46a482063a0bae787
{ "type": "Feature", "properties": { "Name": "William Falk-Wallace", "Description": "Mon Dec  2 18:25:44 EST 2013; Location Accuracy: 77.850269" }, "geometry": { "type": "Point", "coordinates": [ -73.959714, 40.808963, 0.0 ] } },
{ "type": "Feature", "properties": { "Name": "William Falk-Wallace", "Description": "Mon Dec  2 18:20:54 EST 2013; Location Accuracy: 65.000000" }, "geometry": { "type": "Point", "coordinates": [ -73.959689, 40.808917, 0.0 ] } },
{ "type": "Feature", "properties": { "Name": "William Falk-Wallace", "Description": "Mon Dec  2 18:17:04 EST 2013; Location Accuracy: 65.000000" }, "geometry": { "type": "Point", "coordinates": [ -73.959687, 40.808903, 0.0 ] } },
{ "type": "Feature", "properties": { "Name": "William Falk-Wallace", "Description": "Sun Nov 24 23:46:31 EST 2013; Location Accuracy: 65.000000" }, "geometry": { "type": "Point", "coordinates": [ -73.969676, 40.800826, 0.0 ] } }
]}
