{ "type": "FeatureCollection", "crs": { "type": "name", "properties": { "name": "urn:ogc:def:crs:OGC:1.3:CRS84" } }, "features": [ 
{ "type": "Feature", "properties": { "Name": "William Falk-Wallace", "Description": "Mon Dec  2 19:27:58 EST 2013; Location Accuracy: 65.000000" }, "geometry": { "type": "Point", "coordinates": [ -73.959598, 40.809020, 0.0 ] } },
{ "type": "Feature", "properties": { "Name": "William Falk-Wallace", "Description": "Mon Dec  2 19:27:32 EST 2013; Location Accuracy: 65.000000" }, "geometry": { "type": "Point", "coordinates": [ -73.959598, 40.809020, 0.0 ] } },
{ "type": "Feature", "properties": { "Name": "William Falk-Wallace", "Description": "Mon Dec  2 19:22:53 EST 2013; Location Accuracy: 65.000000" }, "geometry": { "type": "Point", "coordinates": [ -73.959568, 40.809041, 0.0 ] } },
{ "type": "Feature", "properties": { "Name": "William Falk-Wallace", "Description": "Mon Dec  2 18:25:44 EST 2013; Location Accuracy: 77.850269" }, "geometry": { "type": "Point", "coordinates": [ -73.959714, 40.808963, 0.0 ] } },
{ "type": "Feature", "properties": { "Name": "William Falk-Wallace", "Description": "Mon Dec  2 18:20:54 EST 2013; Location Accuracy: 65.000000" }, "geometry": { "type": "Point", "coordinates": [ -73.959689, 40.808917, 0.0 ] } },
{ "type": "Feature", "properties": { "Name": "William Falk-Wallace", "Description": "Mon Dec  2 18:17:04 EST 2013; Location Accuracy: 65.000000" }, "geometry": { "type": "Point", "coordinates": [ -73.959687, 40.808903, 0.0 ] } },
{ "type": "Feature", "properties": { "Name": "William Falk-Wallace", "Description": "Sun Nov 24 23:46:31 EST 2013; Location Accuracy: 65.000000" }, "geometry": { "type": "Point", "coordinates": [ -73.969676, 40.800826, 0.0 ] } }
]}
